README.rst
setup.py
examples/py2/__init__.py
examples/py2/simple.py
examples/py3/__init__.py
examples/py3/simple.py
pycdi/__init__.py
pycdi/core.py
pycdi/shortcuts.py
pycdi/utils.py
pycdi.egg-info/PKG-INFO
pycdi.egg-info/SOURCES.txt
pycdi.egg-info/dependency_links.txt
pycdi.egg-info/requires.txt
pycdi.egg-info/top_level.txt
tests/common/__init__.py
tests/common/test_boot.py
tests/common/test_call.py
tests/common/test_cdi.py
tests/common/test_component.py
tests/common/test_container.py
tests/common/test_inheritance.py
tests/common/test_injection_point.py
tests/common/test_interface.py
tests/common/test_producer.py
tests/common/boot/__init__.py
tests/common/boot/load_me_cdi.py
tests/common/boot/deep/__init__.py
tests/common/boot/deep/me_too_cdi.py
tests/py2/__init__.py
tests/py2/unit/__init__.py
tests/py2/unit/test_cdi.py
tests/py2/unit/test_examples.py
tests/py2/unit/test_provide.py
tests/py2/unit/test_singleton.py
tests/py3/__init__.py
tests/py3/unit/__init__.py
tests/py3/unit/test_cdi.py
tests/py3/unit/test_examples.py
tests/py3/unit/test_provide.py
tests/py3/unit/test_type_hint.py