Metadata-Version: 1.1
Name: pycdi
Version: 0.1.2
Summary: Python Code Dependency Injection
Home-page: https://github.com/ettoreleandrotognoli/python-cdi
Author: Éttore Leandro Tognoli
Author-email: ettore.leandro.tognoli@gmail.com
License: BSD
Download-URL: https://github.com/ettoreleandrotognoli/python-cdi/tree/0.1.2/
Keywords: cdi,di,code dependency injection,dependency injection
Platform: UNKNOWN
Classifier: Operating System :: OS Independent
Classifier: Programming Language :: Python
Classifier: Programming Language :: Python :: 2
Classifier: Programming Language :: Python :: 3
Classifier: Development Status :: 2 - Pre-Alpha
Classifier: License :: OSI Approved :: BSD License
